magcoordpy/constants.py
magcoordpy/coord_transforms.py
magcoordpy/data/igrf13coeffs.txt
magcoordpy/helpers.py
magcoordpy/igrf_coeffs.py
magcoordpy-0.2.4.dist-info/METADATA
magcoordpy-0.2.4.dist-info/WHEEL
magcoordpy-0.2.4.dist-info/LICENSE
magcoordpy-0.2.4.dist-info/RECORD
